{
  "project_info": {
    "project_number": "1026894590428",
    "project_id": "prakppbfix",
    "storage_bucket": "prakppbfix.appspot.com"
  },
  "client": [
    {
      "client_info": {
        "mobilesdk_app_id": "1:1026894590428:android:4aa9772a41dc3860885f19",
        "android_client_info": {
          "package_name": "com.example.firebase"
        }
      },
      "oauth_client": [],
      "api_key": [
        {
          "current_key": "AIzaSyADIaY8SZ1iZnRGNqWcucCPhIE23yXYo90"
        }
      ],
      "services": {
        "appinvite_service": {
          "other_platform_oauth_client": []
        }
      }
    }
  ],
  "configuration_version": "1"
}